scapy_utils/__init__.py
scapy_utils/scapy_utils.py
scapy_utils-0.3.9.dist-info/LICENSE
scapy_utils-0.3.9.dist-info/METADATA
scapy_utils-0.3.9.dist-info/WHEEL
scapy_utils-0.3.9.dist-info/top_level.txt
scapy_utils-0.3.9.dist-info/RECORD
