Metadata-Version: 2.1
Name: scapy-utils
Version: 0.3.9
Summary: A collection of utility function for use with Scapy module.
Home-page: UNKNOWN
Author: Max G
Author-email: max3227@gmail.com
License: UNKNOWN
Platform: UNKNOWN
Classifier: Programming Language :: Python :: 3
Classifier: License :: OSI Approved :: MIT License
Classifier: Operating System :: OS Independent
Requires-Python: >=3.8
Requires-Dist: scapy
